beancount_reds_importers/__init__.py
beancount_reds_importers/example/OfxDownload.qfx
beancount_reds_importers/example/README.md
beancount_reds_importers/example/fund_info.py
beancount_reds_importers/example/import.sh
beancount_reds_importers/example/my-smart.import
beancount_reds_importers/example/my.beancount
beancount_reds_importers/example/my.import
beancount_reds_importers/example/transactions.qfx
beancount_reds_importers/importers/__init__.py
beancount_reds_importers/importers/alliant/__init__.py
beancount_reds_importers/importers/ally/__init__.py
beancount_reds_importers/importers/ally/tests/ally_test.py
beancount_reds_importers/importers/ally/tests/transactions.qfx
beancount_reds_importers/importers/ally/tests/transactions.qfx.extract
beancount_reds_importers/importers/ally/tests/transactions.qfx.file_account
beancount_reds_importers/importers/ally/tests/transactions.qfx.file_date
beancount_reds_importers/importers/ally/tests/transactions.qfx.file_name
beancount_reds_importers/importers/amazongc/__init__.py
beancount_reds_importers/importers/amex/__init__.py
beancount_reds_importers/importers/bamboohr/__init__.py
beancount_reds_importers/importers/becu/__init__.py
beancount_reds_importers/importers/capitalonebank/__init__.py
beancount_reds_importers/importers/capitalonebank/tests/360Checking.qfx
beancount_reds_importers/importers/capitalonebank/tests/360Checking.qfx.extract
beancount_reds_importers/importers/capitalonebank/tests/360Checking.qfx.file_account
beancount_reds_importers/importers/capitalonebank/tests/360Checking.qfx.file_date
beancount_reds_importers/importers/capitalonebank/tests/360Checking.qfx.file_name
beancount_reds_importers/importers/capitalonebank/tests/capitalone_test.py
beancount_reds_importers/importers/chase/__init__.py
beancount_reds_importers/importers/citi/__init__.py
beancount_reds_importers/importers/dcu/__init__.py
beancount_reds_importers/importers/dcu/tests/Main_Checking_Account_Transactions.csv
beancount_reds_importers-0.10.0.dist-info/LICENSE
beancount_reds_importers-0.10.0.dist-info/METADATA
beancount_reds_importers-0.10.0.dist-info/WHEEL
beancount_reds_importers-0.10.0.dist-info/entry_points.txt
beancount_reds_importers-0.10.0.dist-info/top_level.txt
beancount_reds_importers-0.10.0.dist-info/RECORD
