Metadata-Version: 2.2
Name: beancount_reds_importers
Version: 0.10.0
Summary: Importers for various institutions for Beancount
Home-page: https://github.com/redstreet/beancount_reds_importers
Author: Red Street
Author-email: redstreet@users.noreply.github.com
License: GPL-3.0
Keywords: importer ingestor beancount accounting
Classifier: Development Status :: 4 - Beta
Classifier: Intended Audience :: Financial and Insurance Industry
Classifier: License :: OSI Approved :: GNU General Public License v3 (GPLv3)
Classifier: Natural Language :: English
Classifier: Programming Language :: Python :: 3 :: Only
Classifier: Programming Language :: Python :: 3.7
Classifier: Topic :: Office/Business :: Financial :: Accounting
Classifier: Topic :: Office/Business :: Financial :: Investment
License-File: LICENSE
Requires-Dist: Click>=7.0
Requires-Dist: beancount<3.0.0,>=2.3.5
Requires-Dist: click_aliases>=1.0.1
Requires-Dist: dateparser>=1.2.0
Requires-Dist: ofxparse>=0.21
Requires-Dist: openpyxl>=3.0.9
Requires-Dist: packaging>=20.3
Requires-Dist: pdfplumber>=0.11.0
Requires-Dist: petl>=1.7.4
Requires-Dist: tabulate>=0.8.9
Requires-Dist: tqdm>=4.64.0
Provides-Extra: dev
Requires-Dist: ruff; extra == "dev"
Requires-Dist: isort; extra == "dev"
Dynamic: author
Dynamic: author-email
Dynamic: classifier
Dynamic: description
Dynamic: description-content-type
Dynamic: home-page
Dynamic: keywords
Dynamic: license
Dynamic: provides-extra
Dynamic: requires-dist
Dynamic: summary
